{
  "app lebels start" :"----------------------------------------------------",
  "label.product.title" : "Mifos-X Client",
  "label.change.language" : "Change language:",
  "label.username" : "UserName",
  "label.password" : "Password",
  "label.signin":"Sign In",
  "label.systemid": "System Id :",
  "label.loanofficer" : "Loan Officer :",
  "label.product.name" : "Mifos X",
  "label.product.version" : "version 1.6.3",
  "label.product.status" : "MifosX is upto date",
  "label.product.aboutus1" : "MifosX is designed by ",
  "label.product.aboutus2" : "global community",
  "label.product.aboutus3" : "working together for poorest, especially women, gain access to financial services.",
  "label.get.involved1" : "Sound interesting?",
  "label.get.involved2" : "Get involved!",
  "label.community.name" : "COSM",
  "label.resources" : "Resources",
  "label.usermanual" : "User manual",
  "label.functional.spec" : "Functional spec",
  "label.faq" : "FAQ",
  "label.community" : "Community",
  "label.users.group" : "User group",
  "label.developer.group" : "Developer group",
  "label.product.irc" : "IRC",
  "label.product.news" : "News and Upcoming events",

 "# common table headings":"....",
  "table.heading.officename":"Office name",
  "table.heading.name":"Name",
  "table.heading.description":"Description",
  "table.heading.filename":"File Name",
  "table.heading.actions":"Actions",
 
 "# common label headings":"....",
  "label.firstname":"First name:",
  "label.lastname":"Last name:",
  "label.office":"Office:",
  "label.currency":"Currency:",
  "label.name":"Name:",
  "label.filename":"File name:",

 "#employee table":"....",
  "table.heading.isLoanOfficer":"Is Loan Officer?",
  "link.create.new.employee":"Create Employee",

  "#view employee":"....",
  "label.employee.isLoanOfficer":"is Loan Officer?:",

  "#view employee":"....",
  "label.office.parentoffice":"label.office.parentoffice:",
  "label.office.openedon":"Opened on:",
  "label.office.namedecorated":"Name Decorated:",
  "label.office.externalid":"External Id:",

  "#view client loan account details":"....",
  "tooltip.addloancharge":"Add Loan Charge",
  "tooltip.addcollateral":"Add Collateral",
  "tooltip.assignloanofficer":"Assign Loan Officer",
  "tooltip.modifyapplication":"Modify Application",
  "tooltip.approve":"Approve",
  "tooltip.reject":"Reject",
  "tooltip.withdrawnbyclient":"Withdrawn By Applicant",
  "tooltip.delete":"Delete",
  "tooltip.guarantor":"Guarantor",
  "tooltip.undoapproval":"Undo Approval",
  "tooltip.disburse":"Disburse",
  "tooltip.Guarantor":"Guarantor",
  "tooltip.undodisbursal":"Undo Disbursal",
  "tooltip.makerepayment":"Make Repayment",
  "tooltip.waiveinterest":"Waive Interest",
  "tooltip.writeoff":"Write-Off",
  "tooltip.close":"Close",

  "label.arrearsby":"Arrears by:",
  "label.status":"status:",
  "label.disbursementdate":"Disbursement date:",
  "label.disburseamount":"Principal amount:",
  "label.loanpurpose":"Loan purpose:",
  "tab.summary":"Summary",
  "tab.accountdetail":"Account details",
  "tab.repaymentschedule":"Repayment schedule",
  "tab.transaction":"Transaction",
  "tab.loandocuments":"Loan documents",
  "tab.notes":"Notes",
  "label.repayments":"Repayments:",
  "label.repaymentstrategy":"Repayment strategy:",
  "label.amortization":"Amortization:",
  "label.interest":"Interest:",
  "label.graceonprincipalpayment":"Grace: On Principal Payment",
  "label.graceoninterestpayment":"Grace: On Interest Payment ",
  "label.submittedondate":"Submitted on:",
  "label.approvedondate":"Approved on:",
  "label.disbursedondate":"Disbursed on:",
  "label.matureson":"Matures on:",
  "label.interestChargedFrom":"Interest charged from:",

  "#summary table":"",
  "table.heading.original":"Original Loan",
  "table.heading.paid":"Paid",
  "table.heading.interest":"Interest",
  "table.heading.penalties":"Penalties",
  "table.heading.total":"Total",
  "table.heading.fees":"Fees",
  "table.heading.waived":"Waived",
  "table.heading.writtenoff":"Writtenoff",
  "table.heading.outstanding":"Outstanding",
  "table.heading.overdue":"Overdue",
  "table.heading.principal":"Principal",

  "#repayment schedule table":"",
  "table.heading.paiddate":"Paid Date",
  "table.heading.loanamountandbalance":"Loan Amount and Balance",
  "table.heading.totalcostofloan":"Total Cost of Loan",
  "table.heading.installmenttotals":"Installment Totals",
  "table.heading.date":"Date",
  "table.heading.days":"# Days",
  "table.heading.disbursement":"Disbursement",
  "table.heading.balanceofloan":"OLB",
  "table.heading.principaldue":"Principal Due",
  "table.heading.principalbalance":"Principal Balance",
  "table.heading.fees":"Fees",
  "table.heading.penalties":"Penalties",
  "table.heading.totaldue":"Total Due",
  "table.heading.totalpaid":"Paid",
  "table.heading.totalpaidinadvance":"In Advance",
  "table.heading.totalpaidlate":"Late",
  "table.heading.totalwaived":"Waived",
  "table.heading.totaloutstanding":"Outstanding",
 
  "#transaction table":"",
  "table.heading.transactiondate":"Transaction Date",
  "table.heading.transactiontype":"Type",
  "table.heading.amount":"Amount",
  "table.heading.breakdown":"Breakdown",
  "table.heading.principal":"principal",
  "table.heading.interest":"Interest",
  "table.heading.fees":"Fees",
  "table.heading.penalities":"penalities",

  "link.home" : "Home",
  "link.tasks" : "Tasks",
  "link.clients" : "Clients",
  "link.accounting": "Accounting",
  "link.reports" : "Reports",
  "link.products" : "Products",
  "link.admin" : "Admin",
  "link.clients.clients" : "Clients",
  "link.clients.groups" : "Groups",
  "link.clients.centers" : "Centers",
  "link.reports.all" : "All",
  "link.reports.clients" : "Clients",
  "link.reports.loans" : "Loans",
  "link.reports.funds" : "Funds",
  "link.reports.accounting" : "Accounting",
  "link.products.loanproducts" : "Loan Products",
  "link.products.savingproducts" : "Saving Products",
  "link.products.productsmix" : "Products Mix",
  "link.products.charges" : "Charges/Penalties",
  "link.admin.users" : "Users",
  "link.admin.organisation" : "Organisation",
  "link.admin.system" : "System",
  "link.profile" : "Profile",
  "link.settings" : "Settings",
  "link.logout" : "LogOut",

  "#accounting coa":"....",
  "button.addaccount":"Add Account",
  "table.heading.accname":"Account name",
  "table.heading.glcode":"GL code",
  "table.heading.acctype": "Account type",
  "table.heading.disabled":"Disabled",
  "table.heading.manualentriesallowed":"Manual Entries Allowed?",
  "table.heading.usedas":"Used as",
  "label.accountname":"Account Name",
  "label.glcode":"GL Code",
  "label.accounttype":"Account Type",
  "label.accountusage":"Account Usage",
  "label.parent":"Select Parent",
  "label.manualentriesallowed":"Manual Entries Allowed?",
  "label.description":"Description",
  "label.tag":"Tag",
  "label.parentaccountname":"Parent Account",


  "#Office ":"....",
  "label.officename":"Office name:",
  "label.openedon":"Opened on:",
  "label.externalId":"External Id:",
  "label.parentoffice":"Parent office:",
  "app lebels end" :"-----------------------------------------------------",		
  "app erros start" :"----------------------------------------------------",		
  "error.login.failed":"Please try again, your credentials are not valid",



  "app erros end" :"------------------------------------------------------"

}